eosPython/__init__.py
eosPython/__version__.py
eosPython/api.py
eosPython/exceptions.py
eosPython/models.py
eosPython/types.py
eosPython/util.py
eosio-py/__init__.py
eosio-py/__version__.py
eosio-py/api.py
eosio-py/exceptions.py
eosio-py/models.py
eosio-py/types.py
eosio-py/util.py
eosiopy/__init__.py
eosiopy/__version__.py
eosiopy/api.py
eosiopy/exceptions.py
eosiopy/models.py
eosiopy/types.py
eosiopy/util.py
telospy/__init__.py
telospy/__version__.py
telospy/api.py
telospy/exceptions.py
telospy/key.py
telospy/models.py
telospy/serialize.py
telospy/types.py
telospy/util.py
telospy-0.1.6.dist-info/METADATA
telospy-0.1.6.dist-info/RECORD
telospy-0.1.6.dist-info/WHEEL
telospy-0.1.6.dist-info/top_level.txt
