Metadata-Version: 2.1
Name: telospy
Version: 0.1.6
Summary: Light weight interface for using EOSIO based RPC APIs
Home-page: http://github.com/Telos-Foundation/telospy
Author: Peter Bue
Author-email: petergrantbue@gmail.com
License: MIT
Platform: UNKNOWN
Requires-Python: >=2.6, !=3.0.*, !=3.1.*, !=3.2.*, !=3.3.*
Requires-Dist: requests (>=2.19.1)
Requires-Dist: numpy (>=1.15.1)
